{
	code: "researchpaperitem",
	heldTpIdleAnimation: "holdbothhandslarge",
	storageFlags: 5,
	behaviors: [{ 
		name: "GroundStorable",
		properties: {
			layout: 'Stacking',
			upSolid: true,
			placeRemoveSound: "game:sounds/block/leather",
			stackingModel: "item/researchpaper-pile",
			collisionBox: { x1: 0.125, y1: 0, z1: 0.125, x2: 0.875, y2: 0.0625, z2: 0.875 },
			cbScaleYByLayer: 0.5,
			modelItemsToStackSizeRatio: 5,
			stackingCapacity: 32,
			transferQuantity: 1,
			bulkTransferQuantity: 3	
		}
	}],
	shape: { base: "item/researchpaper" },
	"textures": {
		"map-blank": { "base": "game:item/lore/map-blank" },
		"pages": { "base": "item/researchpaper" }
	},
	creativeinventory: { "general": ["*"], "items": ["*"], "airship": ["*"] },
	maxstacksize: 30,
	materialDensity: 900,
	guiTransform: {
		translation: { x: 0, y: 0, z: 0 },
		rotation: { x: -65, y: -3, z: 180 },
		origin: { x: 0.47, y: 0.1, z: 0.5 },
		scaleXyz: { x: -1.58, y: 1.58, z: 1.58 }
	},
	tpHandTransform: {
		translation: { x: -0.3, y: -0.1, z: -0.2 },
		rotation: { x: 92, y: -57, z: -71 },
		origin: { x: -0.05, y: -0.2, z: 0.45 },
		scale: 0.43
	},
	groundTransform: {
		translation: { x: 0, y: 0, z: 0 },
		rotation: { x: 0, y: 0, z: 0 },
		origin: { x: 0.5, y: 0, z: 0.5 },
		scale: 4.8
	}
}